{
  "country_code": "VN",
  "country": "Vietnam",
  "city": "Vinh",
  "geonameid": 1562798,
  "target_addresses": 1,
  "samples": [
    {
      "lat": 18.708540815842333,
      "lon": 105.66783281792112,
      "geoinfo": {
        "display_name": "Vinh Hưng Ward, Nghệ An Province, Vietnam",
        "road": null,
        "house_number": null,
        "neighbourhood": null,
        "suburb": null,
        "city_district": null,
        "city": "Vinh Hưng Ward",
        "state": "Nghệ An Province",
        "postcode": null,
        "country": "Vietnam",
        "country_code": "vn"
      },
      "address": "Vinh, Nghệ An Province, Vietnam"
    },
    {
      "lat": 18.698676132342985,
      "lon": 105.70432632129337,
      "geoinfo": {
        "display_name": "Đường Đồng Bồn, Vinh Phú Ward, Nghệ An Province, Vietnam",
        "road": "Đường Đồng Bồn",
        "house_number": null,
        "neighbourhood": null,
        "suburb": null,
        "city_district": null,
        "city": "Vinh Phú Ward",
        "state": "Nghệ An Province",
        "postcode": null,
        "country": "Vietnam",
        "country_code": "vn"
      },
      "address": "969, Đường Đồng Bồn, Vinh Phú Ward, 47503 Nghệ An Province, Vietnam"
    }
  ],
  "updated_at": "2025-10-19T07:30:23.029616+00:00",
  "_kind": "geo_samples"
}