{
  "country_code": "AO",
  "country": "Angola",
  "city": "Luanda",
  "geonameid": 2240449,
  "target_addresses": 2,
  "count": 4,
  "addresses": [
    "867, Largo do Baleizão, Coqueiros, Kinanga, Luanda, Municipality of Luanda, 22086 Luanda Province, Angola",
    "278, Mabunda, Samba Urban District, Luanda, Municipality of Luanda, 89134 Luanda Province, Angola",
    "370, Samba Urban District, Luanda, Municipality of Luanda, 16091 Luanda Province, Angola",
    "021, Areia Branca, Samba Urban District, Luanda, Municipality of Luanda, 11008 Luanda Province, Angola"
  ],
  "updated_at": "2025-10-19T02:43:14.288448+00:00",
  "_kind": "checked_addrs"
}