{
  "country_code": "TH",
  "country": "Thailand",
  "city": "Ban Dung",
  "geonameid": 1619650,
  "target_addresses": 1,
  "samples": [
    {
      "lat": 17.680618759480524,
      "lon": 103.26674842719792,
      "geoinfo": {
        "display_name": "Phon Sung Noi, Ban Dung, Udon Thani Province, Thailand",
        "road": null,
        "house_number": null,
        "neighbourhood": null,
        "suburb": null,
        "city_district": null,
        "city": "Phon Sung Noi",
        "state": null,
        "postcode": null,
        "country": "Thailand",
        "country_code": "th"
      },
      "address": "Ban Dung, Thailand"
    },
    {
      "lat": 17.703258325855277,
      "lon": 103.2565133714239,
      "geoinfo": {
        "display_name": "Ban Dung, Udon Thani Province, 41190, Thailand",
        "road": null,
        "house_number": null,
        "neighbourhood": null,
        "suburb": null,
        "city_district": null,
        "city": "Ban Dung",
        "state": null,
        "postcode": "41190",
        "country": "Thailand",
        "country_code": "th"
      },
      "address": "407, Ban Dung, Udon Thani Province, 41190, Thailand"
    }
  ],
  "updated_at": "2025-10-19T03:56:08.467529+00:00",
  "_kind": "geo_samples"
}