{
  "country_code": "PL",
  "country": "Poland",
  "city": "Jarocin",
  "geonameid": 3097528,
  "target_addresses": 1,
  "samples": [
    {
      "lat": 51.9692858711639,
      "lon": 17.454601630648636,
      "geoinfo": {
        "display_name": "12, Roszków, gmina Jarocin, Jarocin County, Greater Poland Voivodeship, 63-200, Poland",
        "road": "12",
        "house_number": null,
        "neighbourhood": null,
        "suburb": null,
        "city_district": null,
        "city": "Roszków",
        "state": "Greater Poland Voivodeship",
        "postcode": "63-200",
        "country": "Poland",
        "country_code": "pl"
      },
      "address": "12, Jarocin, Greater Poland Voivodeship, Poland"
    },
    {
      "lat": 52.00363690235413,
      "lon": 17.502612445068117,
      "geoinfo": {
        "display_name": "Cielcza, gmina Jarocin, Jarocin County, Greater Poland Voivodeship, 63-200, Poland",
        "road": null,
        "house_number": null,
        "neighbourhood": null,
        "suburb": null,
        "city_district": null,
        "city": "Cielcza",
        "state": "Greater Poland Voivodeship",
        "postcode": "63-200",
        "country": "Poland",
        "country_code": "pl"
      },
      "address": "Cielcza, gmina Jarocin, Jarocin County, Greater Poland Voivodeship, 63-200, Poland"
    }
  ],
  "updated_at": "2025-10-19T06:12:10.488496+00:00",
  "_kind": "geo_samples"
}