{
  "country_code": "SK",
  "country": "Slovakia",
  "city": "Šaľa",
  "geonameid": 3057769,
  "target_addresses": 2,
  "count": 4,
  "addresses": [
    "Dlhá nad Váhom, District of Šaľa, Region of Nitra, Western Slovakia, 925 91, Slovakia",
    "Malý dvorec, Hetméň, Šaľa, District of Šaľa, Region of Nitra, Western Slovakia, 927 01, Slovakia",
    "Šaľa - Veča, Šaľa, District of Šaľa, Region of Nitra, Western Slovakia, 927 05, Slovakia",
    "75, Kráľová nad Váhom, District of Šaľa, Region of Nitra, Western Slovakia, 925 91, Slovakia"
  ],
  "updated_at": "2025-10-19T07:02:34.353795+00:00",
  "_kind": "checked_addrs"
}