{
  "country_code": "TC",
  "country": "Turks and Caicos Islands",
  "city": "Cockburn Town",
  "geonameid": 3576994,
  "target_addresses": 50,
  "count": 24,
  "addresses": [
    "941, Cockburn Town, 25423 Grand Turk, Turks and Caicos Islands",
    "335, North Creek Road, Cockburn Town, 97578 Grand Turk, Turks and Caicos Islands",
    "077, Lighthouse Road, 36862 Cockburn Town, Turks and Caicos Islands",
    "351, Lighthouse Road, Cockburn Town, 28154 Grand Turk, Turks and Caicos Islands",
    "365, Front Street, Cockburn Town, 67026 Grand Turk, Turks and Caicos Islands",
    "500, Missick Road, Cockburn Town, 90818 Grand Turk, Turks and Caicos Islands",
    "683, Smith Lane, Cockburn Town, 01521 Grand Turk, Turks and Caicos Islands",
    "487, Waterloo Road, Cockburn Town, 85271 Grand Turk, Turks and Caicos Islands",
    "431, North Creek Road, 97099 Cockburn Town, Turks and Caicos Islands",
    "670, Airport Road, 99533 Cockburn Town, Turks and Caicos Islands",
    "442, Guy Avenue, Cockburn Town, 36026 Grand Turk, Turks and Caicos Islands",
    "640, Doctors Alley, Cockburn Town, 72568 Grand Turk, Turks and Caicos Islands",
    "580, Close Haul Road, Cockburn Town, 91085 Grand Turk, Turks and Caicos Islands",
    "443, Breezy Brae Road, Cockburn Town, 69219 Grand Turk, Turks and Caicos Islands",
    "441, Darrell's Alley, Cockburn Town, 59191 Grand Turk, Turks and Caicos Islands",
    "113, Christopher Columbus national park Beach access, Cockburn Town, 72683 Grand Turk, Turks and Caicos Islands",
    "546, North Wells Road, Cockburn Town, 81395 Grand Turk, Turks and Caicos Islands",
    "590, John Glenn Road, 52112 Cockburn Town, Turks and Caicos Islands",
    "338, Osbourne Road, Cockburn Town, 83345 Grand Turk, Turks and Caicos Islands",
    "432, Walkin Alley, Cockburn Town, 14462 Grand Turk, Turks and Caicos Islands",
    "364, Palm Grove Drive, Cockburn Town, 25061 Grand Turk, Turks and Caicos Islands",
    "005, Queen Street, Cockburn Town, 88375 Grand Turk, Turks and Caicos Islands",
    "456, Duke Street, 69764 Cockburn Town, Turks and Caicos Islands",
    "775, Canes Alley, Cockburn Town, 94283 Grand Turk, Turks and Caicos Islands"
  ],
  "updated_at": "2025-10-19T05:42:05.913326+00:00",
  "_kind": "checked_addrs"
}