{
  "country_code": "DE",
  "country": "Germany",
  "city": "Papenburg",
  "geonameid": 2855525,
  "target_addresses": 1,
  "samples": [
    {
      "lat": 53.07102504977117,
      "lon": 7.472039216064009,
      "geoinfo": {
        "display_name": "Lüchtenburg rechts, Papenburg, Landkreis Emsland, Lower Saxony, 26871, Germany",
        "road": "Lüchtenburg rechts",
        "house_number": null,
        "neighbourhood": null,
        "suburb": null,
        "city_district": null,
        "city": "Papenburg",
        "state": "Lower Saxony",
        "postcode": "26871",
        "country": "Germany",
        "country_code": "de"
      },
      "address": "Lüchtenburg rechts, Papenburg, Lower Saxony, Germany"
    },
    {
      "lat": 53.09466305893151,
      "lon": 7.369947403488552,
      "geoinfo": {
        "display_name": "Meyer-Werft, Papenburg, Landkreis Emsland, Lower Saxony, 26871, Germany",
        "road": null,
        "house_number": null,
        "neighbourhood": null,
        "suburb": null,
        "city_district": null,
        "city": "Papenburg",
        "state": "Lower Saxony",
        "postcode": "26871",
        "country": "Germany",
        "country_code": "de"
      },
      "address": "252, Meyer-Werft, Papenburg, Landkreis Emsland, Lower Saxony, 26871, Germany"
    }
  ],
  "updated_at": "2025-10-19T03:41:02.617799+00:00",
  "_kind": "geo_samples"
}