{
  "country_code": "ZA",
  "country": "South Africa",
  "city": "Bloemfontein",
  "geonameid": 1018725,
  "target_addresses": 1,
  "samples": [
    {
      "lat": -29.109862397462756,
      "lon": 26.20953978721975,
      "geoinfo": {
        "display_name": "Kellner Street, Mangaung Ward 20, Bloemfontein, Mangaung Metropolitan Municipality, Free State, 9301, South Africa",
        "road": "Kellner Street",
        "house_number": null,
        "neighbourhood": null,
        "suburb": "Mangaung Ward 20",
        "city_district": null,
        "city": "Bloemfontein",
        "state": "Free State",
        "postcode": "9301",
        "country": "South Africa",
        "country_code": "za"
      },
      "address": "Kellner Street, Bloemfontein, Free State, South Africa"
    },
    {
      "lat": -29.132890508435388,
      "lon": 26.21978901637092,
      "geoinfo": {
        "display_name": "Harvey Road, Mangaung Ward 19, Bloemfontein, Mangaung Metropolitan Municipality, Free State, 1903, South Africa",
        "road": "Harvey Road",
        "house_number": null,
        "neighbourhood": null,
        "suburb": "Mangaung Ward 19",
        "city_district": null,
        "city": "Bloemfontein",
        "state": "Free State",
        "postcode": "1903",
        "country": "South Africa",
        "country_code": "za"
      },
      "address": "Harvey Road, Mangaung Ward 19, Bloemfontein, Mangaung Metropolitan Municipality, Free State, 1903, South Africa"
    }
  ],
  "updated_at": "2025-10-19T07:57:04.268160+00:00",
  "_kind": "geo_samples"
}