{
  "country_code": "KH",
  "country": "Cambodia",
  "city": "Battambang",
  "geonameid": 1831797,
  "target_addresses": 4,
  "count": 5,
  "addresses": [
    "028, Khum Norea, Sangkae, Battambang, 021402, Cambodia",
    "564, Battambang, 021402 Battambang, Cambodia",
    "559, Sangkat Sla Kaet, Battambang, 021402, Cambodia",
    "Street 614, Battambang, 021402, Cambodia",
    "Wat Moha Kunakod, Street 609, Sangkat Ratanak, Battambang, 021402, Cambodia"
  ],
  "updated_at": "2025-10-19T07:33:22.977462+00:00",
  "_kind": "checked_addrs"
}