{
  "country_code": "PH",
  "country": "Philippines",
  "city": "Dupax Del Norte",
  "geonameid": 1714052,
  "target_addresses": 1,
  "samples": [
    {
      "lat": 16.32135846844047,
      "lon": 121.07159093838038,
      "geoinfo": {
        "display_name": "Maharlika Highway, Almaguer North, Indiana, Nueva Vizcaya, Cagayan Valley, Philippines",
        "road": "Maharlika Highway",
        "house_number": null,
        "neighbourhood": null,
        "suburb": null,
        "city_district": null,
        "city": "Indiana",
        "state": "Nueva Vizcaya",
        "postcode": null,
        "country": "Philippines",
        "country_code": "ph"
      },
      "address": "854, Maharlika Highway, Almaguer North, Indiana, Nueva Vizcaya, 90442 Cagayan Valley, Philippines"
    }
  ],
  "updated_at": "2025-10-19T05:34:47.496534+00:00",
  "_kind": "geo_samples"
}