{
  "country_code": "AW",
  "country": "Aruba",
  "city": "San Nicolas",
  "geonameid": 3577089,
  "target_addresses": 25,
  "samples": [
    {
      "lat": 12.466520869291454,
      "lon": -69.92565135989128,
      "geoinfo": {
        "display_name": "47, Rooi Koochi, San Nicolas, Aruba, Netherlands",
        "road": "Rooi Koochi",
        "house_number": "47",
        "neighbourhood": null,
        "suburb": null,
        "city_district": null,
        "city": "San Nicolas",
        "state": null,
        "postcode": null,
        "country": "Aruba",
        "country_code": "nl"
      },
      "address": "47 Rooi Koochi, San Nicolas, Aruba"
    },
    {
      "lat": 12.45367753788211,
      "lon": -69.93665550981218,
      "geoinfo": {
        "display_name": "6, Rooi Koochi, Savaneta, Aruba, Netherlands",
        "road": "Rooi Koochi",
        "house_number": "6",
        "neighbourhood": null,
        "suburb": null,
        "city_district": null,
        "city": "Savaneta",
        "state": null,
        "postcode": null,
        "country": "Aruba",
        "country_code": "nl"
      },
      "address": "6 Rooi Koochi, San Nicolas, Aruba"
    },
    {
      "lat": 12.410845420786705,
      "lon": -69.89231677258606,
      "geoinfo": {
        "display_name": "Colony, San Nicolaas, Aruba, Netherlands",
        "road": null,
        "house_number": null,
        "neighbourhood": "Colony",
        "suburb": null,
        "city_district": null,
        "city": "San Nicolaas",
        "state": null,
        "postcode": null,
        "country": "Aruba",
        "country_code": "nl"
      },
      "address": "Colony, San Nicolas, Aruba"
    },
    {
      "lat": 12.413744705307877,
      "lon": -69.94629946243592,
      "geoinfo": {
        "display_name": "Savaneta, Aruba, Netherlands",
        "road": null,
        "house_number": null,
        "neighbourhood": null,
        "suburb": null,
        "city_district": null,
        "city": "Savaneta",
        "state": null,
        "postcode": null,
        "country": "Aruba",
        "country_code": "nl"
      },
      "address": "San Nicolas, Aruba"
    },
    {
      "lat": 12.467381513431087,
      "lon": -69.90911234668127,
      "geoinfo": {
        "display_name": "8, Butucu, San Nicolas, Aruba, Netherlands",
        "road": "Butucu",
        "house_number": "8",
        "neighbourhood": null,
        "suburb": null,
        "city_district": null,
        "city": "San Nicolas",
        "state": null,
        "postcode": null,
        "country": "Aruba",
        "country_code": "nl"
      },
      "address": "8 Butucu, San Nicolas, Aruba"
    },
    {
      "lat": 12.47175184265936,
      "lon": -69.90886300008965,
      "geoinfo": {
        "display_name": "14, Butucu, San Nicolas, Aruba, Netherlands",
        "road": "Butucu",
        "house_number": "14",
        "neighbourhood": null,
        "suburb": null,
        "city_district": null,
        "city": "San Nicolas",
        "state": null,
        "postcode": null,
        "country": "Aruba",
        "country_code": "nl"
      },
      "address": "14 Butucu, San Nicolas, Aruba"
    },
    {
      "lat": 12.444420835534284,
      "lon": -69.87920847107081,
      "geoinfo": {
        "display_name": "Grapefield Raceway, Golfweg, Sabana Lodo, Lago Heights, Aruba, Netherlands",
        "road": "Golfweg",
        "house_number": null,
        "neighbourhood": "Sabana Lodo",
        "suburb": null,
        "city_district": null,
        "city": "Lago Heights",
        "state": null,
        "postcode": null,
        "country": "Aruba",
        "country_code": "nl"
      },
      "address": "Golfweg, San Nicolas, Aruba"
    },
    {
      "lat": 12.457946074406848,
      "lon": -69.9424308254443,
      "geoinfo": {
        "display_name": "213C, Savaneta, Aruba, Netherlands",
        "road": "Savaneta",
        "house_number": "213C",
        "neighbourhood": null,
        "suburb": null,
        "city_district": null,
        "city": "Savaneta",
        "state": null,
        "postcode": null,
        "country": "Aruba",
        "country_code": "nl"
      },
      "address": "213C Savaneta, San Nicolas, Aruba"
    },
    {
      "lat": 12.427881549717823,
      "lon": -69.89505613337953,
      "geoinfo": {
        "display_name": "West Drive, San Nicolaas, Aruba, Netherlands",
        "road": "West Drive",
        "house_number": null,
        "neighbourhood": null,
        "suburb": null,
        "city_district": null,
        "city": "San Nicolaas",
        "state": null,
        "postcode": null,
        "country": "Aruba",
        "country_code": "nl"
      },
      "address": "West Drive, San Nicolas, Aruba"
    },
    {
      "lat": 12.443203908266703,
      "lon": -69.89445350903112,
      "geoinfo": {
        "display_name": "73, Diamantbergweg, San Nicolaas, Aruba, Netherlands",
        "road": "Diamantbergweg",
        "house_number": "73",
        "neighbourhood": null,
        "suburb": null,
        "city_district": null,
        "city": "San Nicolaas",
        "state": null,
        "postcode": null,
        "country": "Aruba",
        "country_code": "nl"
      },
      "address": "73 Diamantbergweg, San Nicolas, Aruba"
    },
    {
      "lat": 12.452861759599273,
      "lon": -69.91889548659768,
      "geoinfo": {
        "display_name": "180B, Caya Bernadina Growell-Kock, Brazil, San Nicolas, Aruba, Netherlands",
        "road": "Caya Bernadina Growell-Kock",
        "house_number": "180B",
        "neighbourhood": null,
        "suburb": null,
        "city_district": null,
        "city": "San Nicolas",
        "state": null,
        "postcode": null,
        "country": "Aruba",
        "country_code": "nl"
      },
      "address": "180B Caya Bernadina Growell-Kock, San Nicolas, Aruba"
    },
    {
      "lat": 12.440643276664845,
      "lon": -69.91574558714707,
      "geoinfo": {
        "display_name": "6A, Nieuweweg, Zeewijk, San Nicolaas, Aruba, Netherlands",
        "road": "Nieuweweg",
        "house_number": "6A",
        "neighbourhood": "Zeewijk",
        "suburb": null,
        "city_district": null,
        "city": "San Nicolaas",
        "state": null,
        "postcode": null,
        "country": "Aruba",
        "country_code": "nl"
      },
      "address": "6A Nieuweweg, San Nicolas, Aruba"
    },
    {
      "lat": 12.423643337537666,
      "lon": -69.87466352422332,
      "geoinfo": {
        "display_name": "Lago Hospital (former), Tenth Avenue, Colony, San Nicolaas, Aruba, Netherlands",
        "road": "Tenth Avenue",
        "house_number": null,
        "neighbourhood": "Colony",
        "suburb": null,
        "city_district": null,
        "city": "San Nicolaas",
        "state": null,
        "postcode": null,
        "country": "Aruba",
        "country_code": "nl"
      },
      "address": "Tenth Avenue, San Nicolas, Aruba"
    },
    {
      "lat": 12.41154663877792,
      "lon": -69.8851416634649,
      "geoinfo": {
        "display_name": "Baby Beach, Colony, San Nicolaas, Aruba, Netherlands",
        "road": "Baby Beach",
        "house_number": null,
        "neighbourhood": "Colony",
        "suburb": null,
        "city_district": null,
        "city": "San Nicolaas",
        "state": null,
        "postcode": null,
        "country": "Aruba",
        "country_code": "nl"
      },
      "address": "Baby Beach, San Nicolas, Aruba"
    },
    {
      "lat": 12.466316823792127,
      "lon": -69.89699904616826,
      "geoinfo": {
        "display_name": "Weg Fontein, Aruba, Netherlands",
        "road": "Weg Fontein",
        "house_number": null,
        "neighbourhood": null,
        "suburb": null,
        "city_district": null,
        "city": null,
        "state": null,
        "postcode": null,
        "country": "Aruba",
        "country_code": "nl"
      },
      "address": "Weg Fontein, San Nicolas, Aruba"
    },
    {
      "lat": 12.459869298943723,
      "lon": -69.89470136394498,
      "geoinfo": {
        "display_name": "152A, Weg Fontein, Aruba, Netherlands",
        "road": "Weg Fontein",
        "house_number": "152A",
        "neighbourhood": null,
        "suburb": null,
        "city_district": null,
        "city": null,
        "state": null,
        "postcode": null,
        "country": "Aruba",
        "country_code": "nl"
      },
      "address": "152A Weg Fontein, San Nicolas, Aruba"
    },
    {
      "lat": 12.452491246914757,
      "lon": -69.9306980435311,
      "geoinfo": {
        "display_name": "48B, Rooi Koochi, Cura Cabai, San Nicolas, Aruba, Netherlands",
        "road": "Rooi Koochi",
        "house_number": "48B",
        "neighbourhood": null,
        "suburb": null,
        "city_district": null,
        "city": "San Nicolas",
        "state": null,
        "postcode": null,
        "country": "Aruba",
        "country_code": "nl"
      },
      "address": "48B Rooi Koochi, San Nicolas, Aruba"
    },
    {
      "lat": 12.456614503492812,
      "lon": -69.9040008099608,
      "geoinfo": {
        "display_name": "Weg Sero Blanco, Aruba, Netherlands",
        "road": "Weg Sero Blanco",
        "house_number": null,
        "neighbourhood": null,
        "suburb": null,
        "city_district": null,
        "city": null,
        "state": null,
        "postcode": null,
        "country": "Aruba",
        "country_code": "nl"
      },
      "address": "Weg Sero Blanco, San Nicolas, Aruba"
    },
    {
      "lat": 12.437311246482288,
      "lon": -69.93584399679465,
      "geoinfo": {
        "display_name": "Cura Cabai, San Nicolas, Aruba, Netherlands",
        "road": "Cura Cabai",
        "house_number": null,
        "neighbourhood": "Cura Cabai",
        "suburb": null,
        "city_district": null,
        "city": "San Nicolas",
        "state": null,
        "postcode": null,
        "country": "Aruba",
        "country_code": "nl"
      },
      "address": "Cura Cabai, San Nicolas, Aruba"
    },
    {
      "lat": 12.440733989242593,
      "lon": -69.92262729874624,
      "geoinfo": {
        "display_name": "126B, Cura Cabai, Aruba, Netherlands",
        "road": "Cura Cabai",
        "house_number": "126B",
        "neighbourhood": null,
        "suburb": null,
        "city_district": null,
        "city": "Cura Cabai",
        "state": null,
        "postcode": null,
        "country": "Aruba",
        "country_code": "nl"
      },
      "address": "126B Cura Cabai, San Nicolas, Aruba"
    },
    {
      "lat": 12.442759177320156,
      "lon": -69.89055150973236,
      "geoinfo": {
        "display_name": "54, Juwana Mortostraat, Sabana Lodo, San Nicolaas, Aruba, Netherlands",
        "road": "Juwana Mortostraat",
        "house_number": "54",
        "neighbourhood": "Sabana Lodo",
        "suburb": null,
        "city_district": null,
        "city": "San Nicolaas",
        "state": null,
        "postcode": null,
        "country": "Aruba",
        "country_code": "nl"
      },
      "address": "54 Juwana Mortostraat, San Nicolas, Aruba"
    },
    {
      "lat": 12.467431071413255,
      "lon": -69.91680402948069,
      "geoinfo": {
        "display_name": "Butucu, San Nicolas, Aruba, Netherlands",
        "road": "Butucu",
        "house_number": null,
        "neighbourhood": null,
        "suburb": null,
        "city_district": null,
        "city": "San Nicolas",
        "state": null,
        "postcode": null,
        "country": "Aruba",
        "country_code": "nl"
      },
      "address": "Butucu, San Nicolas, Aruba"
    },
    {
      "lat": 12.445538145769262,
      "lon": -69.89080358860834,
      "geoinfo": {
        "display_name": "Sero Bentanaweg, Juana Morto, San Nicolas, Aruba, Netherlands",
        "road": "Sero Bentanaweg",
        "house_number": null,
        "neighbourhood": "Juana Morto",
        "suburb": null,
        "city_district": null,
        "city": "San Nicolas",
        "state": null,
        "postcode": null,
        "country": "Aruba",
        "country_code": "nl"
      },
      "address": "Sero Bentanaweg, San Nicolas, Aruba"
    },
    {
      "lat": 12.421213897834672,
      "lon": -69.88977028836094,
      "geoinfo": {
        "display_name": "First Avenue, Sero Colorado, San Nicolaas, Aruba, Netherlands",
        "road": "First Avenue",
        "house_number": null,
        "neighbourhood": "Sero Colorado",
        "suburb": null,
        "city_district": null,
        "city": "San Nicolaas",
        "state": null,
        "postcode": null,
        "country": "Aruba",
        "country_code": "nl"
      },
      "address": "First Avenue, San Nicolas, Aruba"
    },
    {
      "lat": 12.44829619049756,
      "lon": -69.91717544790697,
      "geoinfo": {
        "display_name": "18, Comanchestraat, Brazil, San Nicolas, Aruba, Netherlands",
        "road": "Comanchestraat",
        "house_number": "18",
        "neighbourhood": null,
        "suburb": null,
        "city_district": null,
        "city": "San Nicolas",
        "state": null,
        "postcode": null,
        "country": "Aruba",
        "country_code": "nl"
      },
      "address": "18 Comanchestraat, San Nicolas, Aruba"
    },
    {
      "lat": 12.466658805652296,
      "lon": -69.91292015358674,
      "geoinfo": {
        "display_name": "7, Butucu, San Nicolas, Aruba, Netherlands",
        "road": "Butucu",
        "house_number": "7",
        "neighbourhood": null,
        "suburb": null,
        "city_district": null,
        "city": "San Nicolas",
        "state": null,
        "postcode": null,
        "country": "Aruba",
        "country_code": "nl"
      },
      "address": "7, Butucu, 72597 San Nicolas, Aruba"
    },
    {
      "lat": 12.455320477256592,
      "lon": -69.90356257613544,
      "geoinfo": {
        "display_name": "29S, Weg Sero Blanco, San Nicolas, Aruba, Netherlands",
        "road": "Weg Sero Blanco",
        "house_number": "29S",
        "neighbourhood": null,
        "suburb": null,
        "city_district": null,
        "city": "San Nicolas",
        "state": null,
        "postcode": null,
        "country": "Aruba",
        "country_code": "nl"
      },
      "address": "29S, Weg Sero Blanco, 10215 San Nicolas, Aruba"
    },
    {
      "lat": 12.425395587093835,
      "lon": -69.88216039346013,
      "geoinfo": {
        "display_name": "Tenth Avenue, Sero Colorado, San Nicolaas, Aruba, Netherlands",
        "road": "Tenth Avenue",
        "house_number": null,
        "neighbourhood": "Sero Colorado",
        "suburb": null,
        "city_district": null,
        "city": "San Nicolaas",
        "state": null,
        "postcode": null,
        "country": "Aruba",
        "country_code": "nl"
      },
      "address": "874, Tenth Avenue, 45408 San Nicolas, Aruba"
    },
    {
      "lat": 12.457766332755163,
      "lon": -69.9384879581633,
      "geoinfo": {
        "display_name": "213Z, Savaneta, Aruba, Netherlands",
        "road": "Savaneta",
        "house_number": "213Z",
        "neighbourhood": null,
        "suburb": null,
        "city_district": null,
        "city": "Savaneta",
        "state": null,
        "postcode": null,
        "country": "Aruba",
        "country_code": "nl"
      },
      "address": "213Z, Savaneta, 35193 San Nicolas, Aruba"
    },
    {
      "lat": 12.43114088969944,
      "lon": -69.90469189724304,
      "geoinfo": {
        "display_name": "Lagoweg, Citgo, San Nicolaas, Aruba, Netherlands",
        "road": "Lagoweg",
        "house_number": null,
        "neighbourhood": null,
        "suburb": null,
        "city_district": null,
        "city": "San Nicolaas",
        "state": null,
        "postcode": null,
        "country": "Aruba",
        "country_code": "nl"
      },
      "address": "551, Lagoweg, 69188 San Nicolas, Aruba"
    },
    {
      "lat": 12.447464005755343,
      "lon": -69.9142157713255,
      "geoinfo": {
        "display_name": "10, Huronstraat, Sero Preto, San Nicolas, Aruba, Netherlands",
        "road": "Huronstraat",
        "house_number": "10",
        "neighbourhood": "Sero Preto",
        "suburb": null,
        "city_district": null,
        "city": "San Nicolas",
        "state": null,
        "postcode": null,
        "country": "Aruba",
        "country_code": "nl"
      },
      "address": "10, Huronstraat, 11128 San Nicolas, Aruba"
    },
    {
      "lat": 12.446627517781982,
      "lon": -69.88948549686293,
      "geoinfo": {
        "display_name": "31, Sero Bentanaweg, Juana Morto, San Nicolas, Aruba, Netherlands",
        "road": "Sero Bentanaweg",
        "house_number": "31",
        "neighbourhood": "Juana Morto",
        "suburb": null,
        "city_district": null,
        "city": "San Nicolas",
        "state": null,
        "postcode": null,
        "country": "Aruba",
        "country_code": "nl"
      },
      "address": "31, Sero Bentanaweg, 19115 San Nicolas, Aruba"
    },
    {
      "lat": 12.451318936117035,
      "lon": -69.90259676418542,
      "geoinfo": {
        "display_name": "128, Weg Fontein, Rooi Spoki, Aruba, Netherlands",
        "road": "Weg Fontein",
        "house_number": "128",
        "neighbourhood": "Rooi Spoki",
        "suburb": null,
        "city_district": null,
        "city": null,
        "state": null,
        "postcode": null,
        "country": "Aruba",
        "country_code": "nl"
      },
      "address": "128, Weg Fontein, 03848 San Nicolas, Aruba"
    },
    {
      "lat": 12.450535936744979,
      "lon": -69.89347248414919,
      "geoinfo": {
        "display_name": "Juwana Mortostraat, Juana Morto, San Nicolas, Aruba, Netherlands",
        "road": "Juwana Mortostraat",
        "house_number": null,
        "neighbourhood": "Juana Morto",
        "suburb": null,
        "city_district": null,
        "city": "San Nicolas",
        "state": null,
        "postcode": null,
        "country": "Aruba",
        "country_code": "nl"
      },
      "address": "075, Juwana Mortostraat, 87029 San Nicolas, Aruba"
    },
    {
      "lat": 12.444076342010714,
      "lon": -69.91049589194985,
      "geoinfo": {
        "display_name": "8, Briezenstraat, San Nicolaas, Aruba, Netherlands",
        "road": "Briezenstraat",
        "house_number": "8",
        "neighbourhood": null,
        "suburb": null,
        "city_district": null,
        "city": "San Nicolaas",
        "state": null,
        "postcode": null,
        "country": "Aruba",
        "country_code": "nl"
      },
      "address": "8, Briezenstraat, 97842 San Nicolas, Aruba"
    },
    {
      "lat": 12.447061570625813,
      "lon": -69.92008588320765,
      "geoinfo": {
        "display_name": "108, Caya Jose Geerman, San Nicolaas, Aruba, Netherlands",
        "road": "Caya Jose Geerman",
        "house_number": "108",
        "neighbourhood": null,
        "suburb": null,
        "city_district": null,
        "city": "San Nicolaas",
        "state": null,
        "postcode": null,
        "country": "Aruba",
        "country_code": "nl"
      },
      "address": "108, Caya Jose Geerman, 50534 San Nicolas, Aruba"
    },
    {
      "lat": 12.449001638225731,
      "lon": -69.8916730354838,
      "geoinfo": {
        "display_name": "Aruba Golf Club, Juwana Mortostraat, Juana Morto, San Nicolas, Aruba, Netherlands",
        "road": "Juwana Mortostraat",
        "house_number": null,
        "neighbourhood": "Juana Morto",
        "suburb": null,
        "city_district": null,
        "city": "San Nicolas",
        "state": null,
        "postcode": null,
        "country": "Aruba",
        "country_code": "nl"
      },
      "address": "630, Juwana Mortostraat, 39780 San Nicolas, Aruba"
    },
    {
      "lat": 12.42125194058652,
      "lon": -69.91504719726167,
      "geoinfo": {
        "display_name": "Zeewijk, San Nicolaas, Aruba, Netherlands",
        "road": null,
        "house_number": null,
        "neighbourhood": "Zeewijk",
        "suburb": null,
        "city_district": null,
        "city": "San Nicolaas",
        "state": null,
        "postcode": null,
        "country": "Aruba",
        "country_code": "nl"
      },
      "address": "935, Zeewijk, 82133 San Nicolas, Aruba"
    }
  ],
  "updated_at": "2025-10-19T02:50:09.895256+00:00",
  "_kind": "geo_samples"
}