{
  "country_code": "US",
  "country": "United States",
  "city": "Lewiston Orchards",
  "geonameid": 5598542,
  "target_addresses": 1,
  "samples": [
    {
      "lat": 46.41865687110931,
      "lon": -116.96881872008903,
      "geoinfo": {
        "display_name": "East Main Street, Nez Perce County, Idaho, 83501, United States",
        "road": "East Main Street",
        "house_number": null,
        "neighbourhood": null,
        "suburb": null,
        "city_district": null,
        "city": null,
        "state": "Idaho",
        "postcode": "83501",
        "country": "United States",
        "country_code": "us"
      },
      "address": "937, East Main Street, Nez Perce County, Idaho, 83501, United States"
    }
  ],
  "updated_at": "2025-10-19T06:36:53.513295+00:00",
  "_kind": "geo_samples"
}