{
  "country_code": "VE",
  "country": "Venezuela",
  "city": "Achaguas",
  "geonameid": 3649810,
  "target_addresses": 1,
  "samples": [
    {
      "lat": 7.746457230901255,
      "lon": -68.1971329693848,
      "geoinfo": {
        "display_name": "Caño Seco, Achaguas, Parroquia Achaguas, Municipio Achaguas, Apure State, Venezuela",
        "road": null,
        "house_number": null,
        "neighbourhood": null,
        "suburb": "Caño Seco",
        "city_district": null,
        "city": "Achaguas",
        "state": "Apure State",
        "postcode": null,
        "country": "Venezuela",
        "country_code": "ve"
      },
      "address": "Caño Seco, Achaguas, Apure State, Venezuela"
    },
    {
      "lat": 7.770091013507112,
      "lon": -68.18236402878739,
      "geoinfo": {
        "display_name": "Hato San Luis, Achaguas, Parroquia Achaguas, Municipio Achaguas, Apure State, Venezuela",
        "road": null,
        "house_number": null,
        "neighbourhood": null,
        "suburb": null,
        "city_district": null,
        "city": "Achaguas",
        "state": "Apure State",
        "postcode": null,
        "country": "Venezuela",
        "country_code": "ve"
      },
      "address": "874, Hato San Luis, Achaguas, Parroquia Achaguas, Municipio Achaguas, 15412 Apure State, Venezuela"
    }
  ],
  "updated_at": "2025-10-19T05:00:39.467566+00:00",
  "_kind": "geo_samples"
}