{
  "country_code": "US",
  "country": "United States",
  "city": "Central Falls",
  "geonameid": 5221341,
  "target_addresses": 1,
  "samples": [
    {
      "lat": 41.891150099615686,
      "lon": -71.39805041449293,
      "geoinfo": {
        "display_name": "299, Fuller Avenue, Central Falls, Providence County, Rhode Island, 02863, United States",
        "road": "Fuller Avenue",
        "house_number": "299",
        "neighbourhood": null,
        "suburb": null,
        "city_district": null,
        "city": "Central Falls",
        "state": "Rhode Island",
        "postcode": "02863",
        "country": "United States",
        "country_code": "us"
      },
      "address": "299 Fuller Avenue, Central Falls, Rhode Island, United States"
    }
  ],
  "updated_at": "2025-10-17T00:15:22.837493+00:00",
  "_kind": "geo_samples"
}