{
  "country_code": "JP",
  "country": "Japan",
  "city": "Minamiarupusu",
  "geonameid": 13156739,
  "target_addresses": 1,
  "samples": [
    {
      "lat": 35.58406963874499,
      "lon": 138.4267285052772,
      "geoinfo": {
        "display_name": "Minami-Alps, Minamikoma County, Yamanashi Prefecture, 400-0514, Japan",
        "road": null,
        "house_number": null,
        "neighbourhood": null,
        "suburb": null,
        "city_district": null,
        "city": "Minami-Alps",
        "state": null,
        "postcode": "400-0514",
        "country": "Japan",
        "country_code": "jp"
      },
      "address": "Minamiarupusu, Japan"
    },
    {
      "lat": 35.611202690864594,
      "lon": 138.48595619853432,
      "geoinfo": {
        "display_name": "Terabe, Minami-Alps, Yamanashi Prefecture, 400-0335, Japan",
        "road": null,
        "house_number": null,
        "neighbourhood": null,
        "suburb": null,
        "city_district": null,
        "city": "Minami-Alps",
        "state": null,
        "postcode": "400-0335",
        "country": "Japan",
        "country_code": "jp"
      },
      "address": "Terabe, Minami-Alps, Yamanashi Prefecture, 400-0335, Japan"
    }
  ],
  "updated_at": "2025-10-19T05:33:47.551763+00:00",
  "_kind": "geo_samples"
}