{
  "country_code": "JP",
  "country": "Japan",
  "city": "Tanabe",
  "geonameid": 1850708,
  "target_addresses": 1,
  "samples": [
    {
      "lat": 33.74896242276454,
      "lon": 135.38821129762735,
      "geoinfo": {
        "display_name": "Kisei Expressway, Mutsumi, Tanabe, Wakayama Prefecture, 646-8545, Japan",
        "road": "Kisei Expressway",
        "house_number": null,
        "neighbourhood": null,
        "suburb": null,
        "city_district": null,
        "city": "Tanabe",
        "state": null,
        "postcode": "646-8545",
        "country": "Japan",
        "country_code": "jp"
      },
      "address": "Kisei Expressway, Tanabe, Japan"
    },
    {
      "lat": 33.76462092358062,
      "lon": 135.34341192999725,
      "geoinfo": {
        "display_name": "Hayacho, Tanabe, Wakayama Prefecture, 646-8545, Japan",
        "road": null,
        "house_number": null,
        "neighbourhood": null,
        "suburb": null,
        "city_district": null,
        "city": "Tanabe",
        "state": null,
        "postcode": "646-8545",
        "country": "Japan",
        "country_code": "jp"
      },
      "address": "Hayacho, Tanabe, Wakayama Prefecture, 646-8545, Japan"
    }
  ],
  "updated_at": "2025-10-19T05:00:57.348978+00:00",
  "_kind": "geo_samples"
}