{
  "country_code": "BR",
  "country": "Brazil",
  "city": "Muritiba",
  "geonameid": 3456485,
  "target_addresses": 1,
  "samples": [
    {
      "lat": -12.60882766631174,
      "lon": -39.0134041341419,
      "geoinfo": {
        "display_name": "BA-502, Governador Mangabeira, Região Geográfica Imediata de Cruz das Almas, Região Geográfica Intermediária de Santo Antônio de Jesus, Bahia, Northeast Region, 44350-000, Brazil",
        "road": "BA-502",
        "house_number": null,
        "neighbourhood": null,
        "suburb": null,
        "city_district": "Governador Mangabeira",
        "city": "Governador Mangabeira",
        "state": "Bahia",
        "postcode": "44350-000",
        "country": "Brazil",
        "country_code": "br"
      },
      "address": "BA-502, Muritiba, Bahia, Brazil"
    },
    {
      "lat": -12.607518147261782,
      "lon": -38.974913726078675,
      "geoinfo": {
        "display_name": "Alto da Cruz, São Félix, Região Geográfica Imediata de Cruz das Almas, Região Geográfica Intermediária de Santo Antônio de Jesus, Bahia, Northeast Region, 44360-000, Brazil",
        "road": null,
        "house_number": null,
        "neighbourhood": null,
        "suburb": "Alto da Cruz",
        "city_district": "São Félix",
        "city": "São Félix",
        "state": "Bahia",
        "postcode": "44360-000",
        "country": "Brazil",
        "country_code": "br"
      },
      "address": "Alto da Cruz, São Félix, Região Geográfica Imediata de Cruz das Almas, Região Geográfica Intermediária de Santo Antônio de Jesus, Bahia, Northeast Region, 44360-000, Brazil"
    }
  ],
  "updated_at": "2025-10-19T02:49:43.852334+00:00",
  "_kind": "geo_samples"
}