{
  "country_code": "BR",
  "country": "Brazil",
  "city": "Pirapozinho",
  "geonameid": 3453542,
  "target_addresses": 1,
  "samples": [
    {
      "lat": -22.287371208538524,
      "lon": -51.5267287267693,
      "geoinfo": {
        "display_name": "Jardim São Pedro II, Pirapozinho, Região Imediata de Presidente Prudente, Região Geográfica Intermediária de Presidente Prudente, São Paulo, Southeast Region, 19200-000, Brazil",
        "road": null,
        "house_number": null,
        "neighbourhood": null,
        "suburb": "Jardim São Pedro II",
        "city_district": "Pirapozinho",
        "city": "Pirapozinho",
        "state": "São Paulo",
        "postcode": "19200-000",
        "country": "Brazil",
        "country_code": "br"
      },
      "address": "Jardim São Pedro II, Pirapozinho, Região Imediata de Presidente Prudente, Região Geográfica Intermediária de Presidente Prudente, São Paulo, Southeast Region, 19200-000, Brazil"
    }
  ],
  "updated_at": "2025-10-19T03:09:39.457665+00:00",
  "_kind": "geo_samples"
}